{
    "scene_description_enriched": "The scene depicts a group of figures gathered together, all with golden halos, suggesting they are important religious figures. In the center, a woman in a blue robe with her hands clasped in prayer is prominent. Above them, a dove descends from a radiant light, with rays of light extending downwards. The figures are enclosed within an arched frame, decorated with foliate motifs. The background is a bright blue sky. This scene represents the descent of the Holy Spirit upon the Virgin Mary and the Apostles.",
    "scene_interpretation": "Pentecost",
    "spatial_context": "metaphysical",
    "architectural_context": "no_architecture",
    "building_types": [],
    "architectural_elements": [],
    "persons": [
        "Virgin Mary"
    ],
    "error_type": null,
    "error_message": null,
    "image_url": "https://gallica.bnf.fr/iiif/ark:/12148/btv1b8452807q/f188/1041,223,1366,1720/full/0/default.jpg"
}