{
    "scene_description_enriched": "A youthful figure, likely an angel, is depicted with a halo and blue, feathery wings. The figure wears a white robe adorned with orange bands and holds a long, white scroll or band in its right arm. The background is a rich, textured gold, suggesting a divine or heavenly setting. The figure's hands are raised in a gesture of supplication or greeting.",
    "scene_interpretation": "Annunciation",
    "spatial_context": "metaphysical",
    "architectural_context": "no_architecture",
    "building_types": [],
    "architectural_elements": [],
    "persons": [
        "Angel Gabriel"
    ],
    "error_type": null,
    "error_message": null,
    "image_url": "https://iiif.irht.cnrs.fr/iiif/France/Chantilly/Bibliotheque_du_chateau/M601415401_MS0062/DEPOT/M601415401_MS0062_0196/4906,2004,547,609/full/0/default.jpg"
}