{
    "scene_description_enriched": "A white horse, depicted with a flowing mane and tail, stands in a grassy landscape. A brown lion, with its mouth open and tongue extended, lunges towards the horse, appearing to attack its hindquarters. The background features rolling hills and stylized green foliage under a blue sky. The scene is framed by an ornamental border with red and blue motifs.",
    "scene_interpretation": "This image likely depicts a scene from bestiaries, which were popular in the Middle Ages. The lion and horse often symbolized opposing forces, with the lion representing evil or the devil and the horse representing purity or Christ. The interaction could symbolize the struggle between good and evil.",
    "spatial_context": "outdoor",
    "architectural_context": "no_architecture",
    "building_types": [],
    "architectural_elements": [],
    "persons": [],
    "error_type": null,
    "error_message": null,
    "image_url": "https://gallica.bnf.fr/iiif/ark:/12148/btv1b10527644s/f245/708,2150,523,534/full/0/default.jpg"
}