{
    "scene_description_enriched": "The scene depicts a group of figures with halos, seated and with hands raised in prayer or supplication. Above them, a white dove, symbolizing the Holy Spirit, descends from a golden, textured background that suggests a divine or celestial realm. The figures are rendered in a stylized, medieval manner, with simple drapery and distinct facial features. The overall impression is one of spiritual fervor and divine inspiration.",
    "scene_interpretation": "Pentecost",
    "spatial_context": "metaphysical",
    "architectural_context": "no_architecture",
    "building_types": [],
    "architectural_elements": [],
    "persons": [],
    "error_type": null,
    "error_message": null,
    "image_url": "https://iiif.archive.org/image/iiif/2/lewis_e_110%2Flewis_e_110_jp2.zip%2Flewis_e_110_jp2%2Flewis_e_110_0264.jp2/986,1535,2158,2319/full/0/default.jpg"
}