{
    "scene_description_enriched": "A bearded man with long, flowing grey hair, depicted within a circular frame adorned with foliate motifs, plays a harp-like instrument. He wears a green tunic with gold trim. His gaze is directed forward with a serious expression. The background is a light blue sky with hints of clouds. The overall scene is framed by a decorative border of gold, blue, pink, and red elements, suggesting a miniature from a manuscript.",
    "scene_interpretation": "David in Prayer",
    "spatial_context": "metaphysical",
    "architectural_context": "no_architecture",
    "building_types": [],
    "architectural_elements": [],
    "persons": [
        "David"
    ],
    "error_type": null,
    "error_message": null,
    "image_url": "https://www.e-codices.ch/loris/bge/bge-cl0054/bge-cl0054_199r.jp2/1106,2244,1914,2000/full/0/default.jpg"
}